qc_framework/__init__.py
qc_framework/__main__.py
qc_framework/runtime/__init__.py
qc_framework/runtime/models.py
qc_framework/runtime/runtime.py
asam_qc_framework-1.0.0.dist-info/METADATA
asam_qc_framework-1.0.0.dist-info/WHEEL
asam_qc_framework-1.0.0.dist-info/entry_points.txt
asam_qc_framework-1.0.0.dist-info/RECORD
